README.rst
setup.py
hl/__init__.py
hl/colours.py
hl.colours.egg-info/PKG-INFO
hl.colours.egg-info/SOURCES.txt
hl.colours.egg-info/dependency_links.txt
hl.colours.egg-info/top_level.txt