Metadata-Version: 1.1
Name: hl.colours
Version: 0.1.1
Summary: A simple way to add colours to terminal output in Python.
Home-page: http://github.com/hllau/hl.colours
Author: Hing-Lung Lau
Author-email: lung220@gmail.com
License: Apache v2
Keywords: color colour terminal command line output
Platform: UNKNOWN
Classifier: Environment :: Web Environment
Classifier: Intended Audience :: Developers
Classifier: Programming Language :: Python :: 2.7
Classifier: Topic :: Software Development :: Libraries :: Python Modules
Classifier: License :: OSI Approved :: Apache Software License
